tincan/__init__.py
tincan/about.py
tincan/activity.py
tincan/activity_definition.py
tincan/activity_list.py
tincan/agent.py
tincan/agent_account.py
tincan/agent_list.py
tincan/attachment.py
tincan/attachment_list.py
tincan/base.py
tincan/context.py
tincan/context_activities.py
tincan/extensions.py
tincan/group.py
tincan/http_request.py
tincan/interaction_component.py
tincan/interaction_component_list.py
tincan/language_map.py
tincan/lrs_response.py
tincan/remote_lrs.py
tincan/result.py
tincan/score.py
tincan/serializable_base.py
tincan/statement.py
tincan/statement_base.py
tincan/statement_list.py
tincan/statement_ref.py
tincan/statement_targetable.py
tincan/statements_result.py
tincan/substatement.py
tincan/typed_list.py
tincan/verb.py
tincan/version.py
tincan/conversions/__init__.py
tincan/conversions/iso8601.py
tincan/documents/__init__.py
tincan/documents/activity_profile_document.py
tincan/documents/agent_profile_document.py
tincan/documents/document.py
tincan/documents/state_document.py
edx_tincan_py35-2.0.0.dist-info/LICENSE
edx_tincan_py35-2.0.0.dist-info/METADATA
edx_tincan_py35-2.0.0.dist-info/NOTICE
edx_tincan_py35-2.0.0.dist-info/WHEEL
edx_tincan_py35-2.0.0.dist-info/top_level.txt
edx_tincan_py35-2.0.0.dist-info/RECORD
