Metadata-Version: 2.2
Name: edx-tincan-py35
Version: 2.0.0
Summary: A Python 3 library for implementing Tin Can API.
Home-page: http://rusticisoftware.github.io/TinCanPython/
Author: edX
Author-email: oscm@edx.org
Maintainer-email: mailto:brian.miller@tincanapi.com
License: Apache License 2.0
Keywords: Tin Can,TinCan,Tin Can API,TinCanAPI,Experience API,xAPI,SCORM,AICC
Classifier: Programming Language :: Python :: 3
Classifier: Programming Language :: Python :: 3.11
Classifier: Programming Language :: Python :: 3.12
License-File: LICENSE
License-File: NOTICE
Requires-Dist: aniso8601
Requires-Dist: pytz
Dynamic: author
Dynamic: author-email
Dynamic: classifier
Dynamic: home-page
Dynamic: keywords
Dynamic: license
Dynamic: maintainer-email
Dynamic: requires-dist
Dynamic: summary
